{
  "resultCount": 2,
  "results": [
    {
      "wrapperType": "track",
      "kind": "feature-movie",
      "trackId": 978638765,
      "artistName": "George Lucas",
      "trackName": "Star Wars: Episode IV - A New Hope",
      "trackCensoredName": "Star Wars: Episode IV - A New Hope",
      "trackViewUrl": "https://tv.apple.com/us/movie/star-wars-episode-iv-a-new-hope/umc.cmc.1hgm1h1iwn4r8cjbx3x9thx6k",
      "previewUrl": "https://video-ssl.itunes.apple.com/itunes-assets/Video113/v4/f3/1b/2e/f31b2e87-4561-4def-4332-f0e1f2c3e3a9/mzvf_8773264455154177671.640x352.h264lc.U.p.m4v",
      "artworkUrl30": "https://is1-ssl.mzstatic.com/image/thumb/Video125/v4/94/21/6d/94216d48-f1e0-7c1c-1d9e-7d5c2e1a2e8d/source/30x30bb.jpg",
      "artworkUrl60": "https://is1-ssl.mzstatic.com/image/thumb/Video125/v4/94/21/6d/94216d48-f1e0-7c1c-1d9e-7d5c2e1a2e8d/source/60x60bb.jpg",
      "artworkUrl100": "https://is1-ssl.mzstatic.com/image/thumb/Video125/v4/94/21/6d/94216d48-f1e0-7c1c-1d9e-7d5c2e1a2e8d/source/100x100bb.jpg",
      "collectionPrice": 19.99,
      "trackPrice": 14.99,
      "trackRentalPrice": 3.99,
      "collectionHDPrice": 19.99,
      "trackHDPrice": 19.99,
      "trackHDRentalPrice": 3.99,
      "releaseDate": "1977-05-25T07:00:00Z",
      "collectionExplicitness": "notExplicit",
      "trackExplicitness": "notExplicit",
      "trackTimeMillis": 7260000,
      "country": "USA",
      "currency": "USD",
      "primaryGenreName": "Sci-Fi & Fantasy",
      "contentAdvisoryRating": "PG",
      "longDescription": "The Jedi Knights have been exterminated and the Empire rules the galaxy with an iron fist.",
      "hasITunesExtras": true
    },
    {
      "wrapperType": "track",
      "kind": "feature-movie",
      "trackId": 978638766,
      "artistName": "Irvin Kershner",
      "trackName": "Star Wars: The Empire Strikes Back",
      "trackCensoredName": "Star Wars: The Empire Strikes Back",
      "trackViewUrl": "https://tv.apple.com/us/movie/star-wars-the-empire-strikes-back/umc.cmc.5983l0r7p3u8ljp9b6v4hm8vl",
      "previewUrl": "https://video-ssl.itunes.apple.com/itunes-assets/Video116/v4/b2/9c/84/b29c8482-5e85-7c8f-4c3a-cd4df2e2e8e1/mzvf_8773264455154177672.640x352.h264lc.U.p.m4v",
      "artworkUrl30": "https://is1-ssl.mzstatic.com/image/thumb/Video115/v4/a9/82/26/a98226e4-f2e0-5c8c-9d1e-7d5c2e1a2e8e/source/30x30bb.jpg",
      "artworkUrl60": "https://is1-ssl.mzstatic.com/image/thumb/Video115/v4/a9/82/26/a98226e4-f2e0-5c8c-9d1e-7d5c2e1a2e8e/source/60x60bb.jpg",
      "artworkUrl100": "https://is1-ssl.mzstatic.com/image/thumb/Video115/v4/a9/82/26/a98226e4-f2e0-5c8c-9d1e-7d5c2e1a2e8e/source/100x100bb.jpg",
      "collectionPrice": 19.99,
      "trackPrice": 14.99,
      "trackRentalPrice": 3.99,
      "collectionHDPrice": 19.99,
      "trackHDPrice": 19.99,
      "trackHDRentalPrice": 3.99,
      "releaseDate": "1980-06-20T07:00:00Z",
      "collectionExplicitness": "notExplicit",
      "trackExplicitness": "notExplicit",
      "trackTimeMillis": 7440000,
      "country": "USA",
      "currency": "USD",
      "primaryGenreName": "Sci-Fi & Fantasy",
      "contentAdvisoryRating": "PG",
      "longDescription": "The Imperial forces, under orders from cruel Darth Vader, hold Princess Leia hostage.",
      "hasITunesExtras": true
    }
  ]
}