{
  "category": "mdm/profiles",
  "name": "com.apple.profileRemovalPassword",
  "title": "Profile Removal Password",
  "description": "The payload that configures profile removal.",
  "payload": {
    "payloadtype": "com.apple.profileRemovalPassword",
    "supportedOS": {
      "iOS": {
        "introduced": "4.0"
      },
      "macOS": {
        "introduced": "10.7"
      },
      "tvOS": {
        "introduced": "9.0"
      },
      "visionOS": {
        "introduced": "n/a"
      },
      "watchOS": {
        "introduced": "n/a"
      }
    }
  },
  "payloadkeys": [
    {
      "key": "RemovalPassword",
      "title": "Removal Password",
      "type": "\u003cstring\u003e",
      "presence": "optional",
      "content": "The password to allow removing the profile."
    }
  ]
}
